nlu/__init__.py
nlu/discovery.py
nlu/finance.py
nlu/info.py
nlu/spellbook.py
nlu/components/__init__.py
nlu/components/assertions/__init__.py
nlu/components/assertions/assertion_dl/__init__.py
nlu/components/assertions/assertion_dl/assertion_dl.py
nlu/components/assertions/assertion_dl/component_infos.json
nlu/components/assertions/assertion_log_reg/__init__.py
nlu/components/assertions/assertion_log_reg/assertion_log_reg.py
nlu/components/assertions/assertion_log_reg/component_infos.json
nlu/components/chunkers/__init__.py
nlu/components/chunkers/chunk_mapper/__init__.py
nlu/components/chunkers/chunk_mapper/chunk_mapper.py
nlu/components/chunkers/chunk_mapper/component_infos.json
nlu/components/chunkers/contextual_parser/__init__.py
nlu/components/chunkers/contextual_parser/component_infos.json
nlu/components/chunkers/contextual_parser/contextual_parser.py
nlu/components/chunkers/default_chunker/__init__.py
nlu/components/chunkers/default_chunker/component_infos.json
nlu/components/chunkers/default_chunker/default_chunker.py
nlu/components/chunkers/ngram/__init__.py
nlu/components/chunkers/ngram/component_infos.json
nlu/components/chunkers/ngram/ngram.py
nlu/components/classifiers/__init__.py
nlu/components/classifiers/classifier_dl/__init__.py
nlu/components/classifiers/classifier_dl/classifier_dl.py
nlu/components/classifiers/classifier_dl/component_infos.json
nlu/components/classifiers/generic_classifier/__init__.py
nlu/components/classifiers/generic_classifier/component_infos.json
nlu/components/classifiers/generic_classifier/generic_classifier.py
nlu/components/classifiers/language_detector/__init__.py
nlu/components/classifiers/language_detector/component_infos.json
nlu/components/classifiers/language_detector/language_detector.py
nlu/components/classifiers/multi_classifier/__init__.py
nlu/components/classifiers/multi_classifier/component_infos.json
nlu/components/classifiers/multi_classifier/multi_classifier.py
nlu1213-4.0.0.dist-info/LICENSE
nlu1213-4.0.0.dist-info/METADATA
nlu1213-4.0.0.dist-info/WHEEL
nlu1213-4.0.0.dist-info/top_level.txt
nlu1213-4.0.0.dist-info/RECORD
